openapi/_hooks/registration.py
youdotcom/__init__.py
youdotcom/_version.py
youdotcom/agents.py
youdotcom/basesdk.py
youdotcom/contents_sdk.py
youdotcom/httpclient.py
youdotcom/py.typed
youdotcom/runs.py
youdotcom/sdk.py
youdotcom/sdkconfiguration.py
youdotcom/search.py
youdotcom/_hooks/__init__.py
youdotcom/_hooks/registration.py
youdotcom/_hooks/sdkhooks.py
youdotcom/_hooks/types.py
youdotcom/errors/__init__.py
youdotcom/errors/agentruns400response_error.py
youdotcom/errors/agentruns401response_error.py
youdotcom/errors/agentruns422response_error.py
youdotcom/errors/contentsop.py
youdotcom/errors/no_response_error.py
youdotcom/errors/responsevalidationerror.py
youdotcom/errors/searchop.py
youdotcom/errors/youdefaulterror.py
youdotcom/errors/youerror.py
youdotcom/models/__init__.py
youdotcom/models/advancedagentrunsrequest.py
youdotcom/models/agentruns422response_error.py
youdotcom/models/agentrunsbatchresponse.py
youdotcom/models/agentrunsresponseoutput.py
youdotcom/models/agentrunsresponsewebsearchresult.py
youdotcom/models/agentrunsstreamingresponse.py
youdotcom/models/agentsrunsop.py
youdotcom/models/computetool.py
youdotcom/models/contents.py
youdotcom/models/contentsformats.py
youdotcom/models/contentsmetadata.py
youdotcom/models/contentsop.py
youdotcom/models/country.py
youdotcom/models/customagentrunsrequest.py
youdotcom/models/expressagentrunsrequest.py
youdotcom/models/freshness.py
youdotcom/models/language.py
youdotcom/models/livecrawl.py
youdotcom/models/livecrawlformats.py
youdotcom/models/reportverbosity.py
youdotcom/models/researchtool.py
youdotcom/models/response_created.py
youdotcom/models/response_done.py
youdotcom/models/response_output_content_full.py
youdotcom/models/response_output_item_added.py
youdotcom/models/response_output_item_done.py
youdotcom/models/response_output_text_delta.py
youdotcom/models/response_starting.py
youdotcom/models/safesearch.py
youdotcom/models/searcheffort.py
youdotcom/models/searchop.py
youdotcom/models/security.py
youdotcom-2.2.0.dist-info/METADATA
youdotcom-2.2.0.dist-info/WHEEL
youdotcom-2.2.0.dist-info/top_level.txt
youdotcom-2.2.0.dist-info/RECORD
