Metadata-Version: 2.4
Name: youdotcom
Version: 2.2.0
Summary: The official You.com Python SDK.
Author: You.com
License: Apache-2.0
Requires-Python: >=3.9.2
Requires-Dist: httpcore>=1.0.9
Requires-Dist: httpx>=0.28.1
Requires-Dist: pydantic>=2.11.2
